{
    "data": {
        "items": [
            {
                "Id": 168,
                "ReferenceId": "20230321fzOdmz3",
                "StoreId": 1,
                "UserId": 13,
                "UserTokenId": 259,
                "OrderStatus": "SUCCESSFUL",
                "TotalBeforeTax": 45000,
                "TotalTax": 4500,
                "DeliveryFee": 0,
                "OrderFee": 1000,
                "PaymentFee": 0,
                "Total": 50500,
                "Metadata": "{\"order\": {\"amount\": 50500, \"invoice_number\": \"20230321fzOdmz3\"}, \"channel\": {\"id\": \"VIRTUAL_ACCOUNT_BCA\", \"name\": \"\"}, \"service\": {\"id\": \"VIRTUAL_ACCOUNT\", \"name\": \"\"}, \"acquirer\": {\"id\": \"BCA\", \"name\": \"\"}, \"transaction\": {\"date\": \"2023-03-21T02:17:24Z\", \"status\": \"SUCCESS\", \"original_request_id\": \"b209982a-395c-497e-b284-7bec4584c5b4\"}, \"virtual_account_info\": {\"virtual_account_number\": \"1900800000030899\"}, \"virtual_account_payment\": {\"date\": \"20230321091724\", \"identifier\": [{\"name\": \"REQUEST_ID\", \"value\": \"559362\"}, {\"name\": \"REFERENCE\", \"value\": \"04730\"}, {\"name\": \"CHANNEL_TYPE\", \"value\": \"6014\"}], \"reference_number\": \"04730\"}}",
                "ItemQty": 3,
                "ExpiredAt": "2023-03-21T02:47:24.627142Z",
                "CreatedAt": "2023-03-21T02:16:21.308888Z",
                "UpdatedAt": "2023-03-21T02:16:21.308888Z",
                "DeletedAt": null,
                "UserName": "Feryanti",
                "PhoneNumber": "628119199509",
                "MerchantId": 1,
                "DeliveryMethod": "PICKUP",
                "DeliveryRefId": null,
                "DeliveryUrl": null,
                "IsPaid": true,
                "PaymentMethod": "BCA-VA",
                "PaymentCode": "BCA-VA",
                "PaymentUrl": "",
                "Forwarded": null,
                "Name": "Lotte Grosir Fatmawati",
                "Address": "",
                "City": "",
                "Country": "",
                "MaxRadius": 0,
                "MerchantName": "",
                "Pic": "",
                "Admin": "",
                "IsActive": false,
                "ZipCode": "",
                "CategoryId": 0,
                "CategoryName": "",
                "MinStock": 0,
                "MaxSalesDays": 0,
                "Token": "",
                "MerchantID": 0,
                "State": "",
                "LocationName": "Jl. H. Unus No.48, RT.002/RW.001, Larangan Utara, Kec. Larangan, Kota Tangerang, Banten 15154, Indonesia",
                "LocationNote": null,
                "AddressId": null,
                "ExpireAt": "0001-01-01T00:00:00Z",
                "OrderItem": null
            },
            {
                "Id": 163,
                "ReferenceId": "202303207UHKpML",
                "StoreId": 1,
                "UserId": 13,
                "UserTokenId": 252,
                "OrderStatus": "SUCCESSFUL",
                "TotalBeforeTax": 30000,
                "TotalTax": 3000,
                "DeliveryFee": 10150,
                "OrderFee": 1000,
                "PaymentFee": 0,
                "Total": 44150,
                "Metadata": "{\"order\": {\"amount\": 44150, \"invoice_number\": \"202303207UHKpML\"}, \"channel\": {\"id\": \"VIRTUAL_ACCOUNT_BCA\", \"name\": \"\"}, \"service\": {\"id\": \"VIRTUAL_ACCOUNT\", \"name\": \"\"}, \"acquirer\": {\"id\": \"BCA\", \"name\": \"\"}, \"transaction\": {\"date\": \"2023-03-20T04:10:24Z\", \"status\": \"SUCCESS\", \"original_request_id\": \"f0c602e0-5d04-4951-bb56-a1cc23ce2b75\"}, \"virtual_account_info\": {\"virtual_account_number\": \"1900800000030793\"}, \"virtual_account_payment\": {\"date\": \"20230320111024\", \"identifier\": [{\"name\": \"REQUEST_ID\", \"value\": \"132203\"}, {\"name\": \"REFERENCE\", \"value\": \"17143\"}, {\"name\": \"CHANNEL_TYPE\", \"value\": \"6014\"}], \"reference_number\": \"17143\"}}",
                "ItemQty": 2,
                "ExpiredAt": "2023-03-20T04:40:24.531397Z",
                "CreatedAt": "2023-03-20T04:09:34.673773Z",
                "UpdatedAt": "2023-03-20T04:09:34.673773Z",
                "DeletedAt": null,
                "UserName": "Feryanti",
                "PhoneNumber": "628119199509",
                "MerchantId": 1,
                "DeliveryMethod": "jne",
                "DeliveryRefId": null,
                "DeliveryUrl": null,
                "IsPaid": true,
                "PaymentMethod": "BCA-VA",
                "PaymentCode": "BCA-VA",
                "PaymentUrl": "",
                "Forwarded": null,
                "Name": "Lotte Grosir Fatmawati",
                "Address": "",
                "City": "",
                "Country": "",
                "MaxRadius": 0,
                "MerchantName": "",
                "Pic": "",
                "Admin": "",
                "IsActive": false,
                "ZipCode": "",
                "CategoryId": 0,
                "CategoryName": "",
                "MinStock": 0,
                "MaxSalesDays": 0,
                "Token": "",
                "MerchantID": 0,
                "State": "",
                "LocationName": "Jl. Pulau Sipura, RT.003/RW.010, Jatimakmur, Kec. Pd. Gede, Kota Bks, Jawa Barat 17413, Indonesia",
                "LocationNote": null,
                "AddressId": null,
                "ExpireAt": "0001-01-01T00:00:00Z",
                "OrderItem": null
            },
            {
                "Id": 154,
                "ReferenceId": "20230317jhLOP1B",
                "StoreId": 1,
                "UserId": 19,
                "UserTokenId": 245,
                "OrderStatus": "SUCCESSFUL",
                "TotalBeforeTax": 20000,
                "TotalTax": 2000,
                "DeliveryFee": 16100,
                "OrderFee": 1000,
                "PaymentFee": 0,
                "Total": 39100,
                "Metadata": "{\"order\": {\"amount\": 39100, \"invoice_number\": \"20230317jhLOP1B\"}, \"channel\": {\"id\": \"EMONEY_SHOPEE_PAY\", \"name\": \"\"}, \"service\": {\"id\": \"EMONEY\", \"name\": \"\"}, \"acquirer\": {\"id\": \"SHOPEE_PAY\", \"name\": \"\"}, \"transaction\": {\"date\": \"2023-03-17T09:17:48Z\", \"status\": \"SUCCESS\", \"original_request_id\": \"20230317jhLOP1B\"}, \"virtual_account_info\": {\"virtual_account_number\": \"\"}, \"virtual_account_payment\": {\"date\": \"\", \"identifier\": null, \"reference_number\": \"\"}}",
                "ItemQty": 1,
                "ExpiredAt": "2023-03-17T09:47:48.909725Z",
                "CreatedAt": "2023-03-17T09:17:41.231978Z",
                "UpdatedAt": "2023-03-17T09:17:41.231978Z",
                "DeletedAt": null,
                "UserName": "Atha Dhaiffathin 2nd",
                "PhoneNumber": "628974500107",
                "MerchantId": 1,
                "DeliveryMethod": "grab",
                "DeliveryRefId": "WYB-1679044792469",
                "DeliveryUrl": "",
                "IsPaid": true,
                "PaymentMethod": "SHOPEEPAY",
                "PaymentCode": "SHOPEEPAY",
                "PaymentUrl": "https://sandbox.doku.com/integration/simulator/shopeepay/payment?amount=3910000&&invoiceNumber=20230317jhLOP1B&&mei=BRN-0298-1676891848212&&sei=BRN-0298-1676891848212&&token=zKyPnnnINQWJkSTgjwDHmt058dSuUs0IQpnGZZczGYcbW0fds7IrylMEsB2G6jq1Y2pqlJX3udUpapuW5l5hygz66HYr5gJvwvRz5zdt8OUbJ57k2HmBcyb8MIiEBxDD&&returnUrl=https://jcc-file.jatismobile.com/thankyou",
                "Forwarded": null,
                "Name": "Lotte Grosir Fatmawati",
                "Address": "",
                "City": "",
                "Country": "",
                "MaxRadius": 0,
                "MerchantName": "",
                "Pic": "",
                "Admin": "",
                "IsActive": false,
                "ZipCode": "",
                "CategoryId": 0,
                "CategoryName": "",
                "MinStock": 0,
                "MaxSalesDays": 0,
                "Token": "",
                "MerchantID": 0,
                "State": "",
                "LocationName": "Graha Mitra Citra Blok H11/2, RT.10/RW.02, Panongan, Kec. Panongan, Kabupaten Tangerang, Banten 15710, Indonesia",
                "LocationNote": null,
                "AddressId": null,
                "ExpireAt": "0001-01-01T00:00:00Z",
                "OrderItem": null
            },
            {
                "Id": 152,
                "ReferenceId": "20230317NwcGRue",
                "StoreId": 1,
                "UserId": 13,
                "UserTokenId": 243,
                "OrderStatus": "SUCCESSFUL",
                "TotalBeforeTax": 40000,
                "TotalTax": 4000,
                "DeliveryFee": 0,
                "OrderFee": 1000,
                "PaymentFee": 0,
                "Total": 45000,
                "Metadata": "{\"order\": {\"amount\": 45000, \"invoice_number\": \"20230317NwcGRue\"}, \"channel\": {\"id\": \"VIRTUAL_ACCOUNT_BCA\", \"name\": \"\"}, \"service\": {\"id\": \"VIRTUAL_ACCOUNT\", \"name\": \"\"}, \"acquirer\": {\"id\": \"BCA\", \"name\": \"\"}, \"transaction\": {\"date\": \"2023-03-17T08:55:42Z\", \"status\": \"SUCCESS\", \"original_request_id\": \"26325154-900f-486c-bb88-5796012ee55a\"}, \"virtual_account_info\": {\"virtual_account_number\": \"1900800000030645\"}, \"virtual_account_payment\": {\"date\": \"20230317155542\", \"identifier\": [{\"name\": \"REQUEST_ID\", \"value\": \"267451\"}, {\"name\": \"REFERENCE\", \"value\": \"10920\"}, {\"name\": \"CHANNEL_TYPE\", \"value\": \"6014\"}], \"reference_number\": \"10920\"}}",
                "ItemQty": 2,
                "ExpiredAt": "2023-03-17T09:25:43.006031Z",
                "CreatedAt": "2023-03-17T08:54:15.186312Z",
                "UpdatedAt": "2023-03-17T08:54:15.186312Z",
                "DeletedAt": null,
                "UserName": "Feryanti",
                "PhoneNumber": "628119199509",
                "MerchantId": 1,
                "DeliveryMethod": "PICKUP",
                "DeliveryRefId": null,
                "DeliveryUrl": null,
                "IsPaid": true,
                "PaymentMethod": "BCA-VA",
                "PaymentCode": "BCA-VA",
                "PaymentUrl": "",
                "Forwarded": null,
                "Name": "Lotte Grosir Fatmawati",
                "Address": "",
                "City": "",
                "Country": "",
                "MaxRadius": 0,
                "MerchantName": "",
                "Pic": "",
                "Admin": "",
                "IsActive": false,
                "ZipCode": "",
                "CategoryId": 0,
                "CategoryName": "",
                "MinStock": 0,
                "MaxSalesDays": 0,
                "Token": "",
                "MerchantID": 0,
                "State": "",
                "LocationName": "Jl. Pulau Sipura, RT.003/RW.010, Jatimakmur, Kec. Pd. Gede, Kota Bks, Jawa Barat 17413, Indonesia",
                "LocationNote": null,
                "AddressId": null,
                "ExpireAt": "0001-01-01T00:00:00Z",
                "OrderItem": null
            },
            {
                "Id": 150,
                "ReferenceId": "20230317IOlUvfK",
                "StoreId": 1,
                "UserId": 13,
                "UserTokenId": 241,
                "OrderStatus": "SUCCESSFUL",
                "TotalBeforeTax": 20000,
                "TotalTax": 2000,
                "DeliveryFee": 0,
                "OrderFee": 1000,
                "PaymentFee": 0,
                "Total": 23000,
                "Metadata": "{\"order\": {\"amount\": 23000, \"invoice_number\": \"20230317IOlUvfK\"}, \"channel\": {\"id\": \"VIRTUAL_ACCOUNT_BCA\", \"name\": \"\"}, \"service\": {\"id\": \"VIRTUAL_ACCOUNT\", \"name\": \"\"}, \"acquirer\": {\"id\": \"BCA\", \"name\": \"\"}, \"transaction\": {\"date\": \"2023-03-17T08:45:49Z\", \"status\": \"SUCCESS\", \"original_request_id\": \"f68d070e-523f-4d68-8c11-d25311cbe0b3\"}, \"virtual_account_info\": {\"virtual_account_number\": \"1900800000030639\"}, \"virtual_account_payment\": {\"date\": \"20230317154549\", \"identifier\": [{\"name\": \"REQUEST_ID\", \"value\": \"706228\"}, {\"name\": \"REFERENCE\", \"value\": \"38564\"}, {\"name\": \"CHANNEL_TYPE\", \"value\": \"6014\"}], \"reference_number\": \"38564\"}}",
                "ItemQty": 1,
                "ExpiredAt": "2023-03-17T09:15:49.756672Z",
                "CreatedAt": "2023-03-17T08:45:29.728364Z",
                "UpdatedAt": "2023-03-17T08:45:29.728364Z",
                "DeletedAt": null,
                "UserName": "Feryanti",
                "PhoneNumber": "628119199509",
                "MerchantId": 1,
                "DeliveryMethod": "PICKUP",
                "DeliveryRefId": null,
                "DeliveryUrl": null,
                "IsPaid": true,
                "PaymentMethod": "BCA-VA",
                "PaymentCode": "BCA-VA",
                "PaymentUrl": "",
                "Forwarded": null,
                "Name": "Lotte Grosir Fatmawati",
                "Address": "",
                "City": "",
                "Country": "",
                "MaxRadius": 0,
                "MerchantName": "",
                "Pic": "",
                "Admin": "",
                "IsActive": false,
                "ZipCode": "",
                "CategoryId": 0,
                "CategoryName": "",
                "MinStock": 0,
                "MaxSalesDays": 0,
                "Token": "",
                "MerchantID": 0,
                "State": "",
                "LocationName": "Jl. Pulau Sipura, RT.003/RW.010, Jatimakmur, Kec. Pd. Gede, Kota Bks, Jawa Barat 17413, Indonesia",
                "LocationNote": null,
                "AddressId": null,
                "ExpireAt": "0001-01-01T00:00:00Z",
                "OrderItem": null
            },
            {
                "Id": 149,
                "ReferenceId": "20230317AEMAdP2",
                "StoreId": 1,
                "UserId": 13,
                "UserTokenId": 239,
                "OrderStatus": "SUCCESSFUL",
                "TotalBeforeTax": 15000,
                "TotalTax": 1500,
                "DeliveryFee": 0,
                "OrderFee": 1000,
                "PaymentFee": 0,
                "Total": 17500,
                "Metadata": "{\"order\": {\"amount\": 17500, \"invoice_number\": \"20230317AEMAdP2\"}, \"channel\": {\"id\": \"VIRTUAL_ACCOUNT_BCA\", \"name\": \"\"}, \"service\": {\"id\": \"VIRTUAL_ACCOUNT\", \"name\": \"\"}, \"acquirer\": {\"id\": \"BCA\", \"name\": \"\"}, \"transaction\": {\"date\": \"2023-03-17T08:41:20Z\", \"status\": \"SUCCESS\", \"original_request_id\": \"909d9627-6871-4e93-818b-bfe40a854c56\"}, \"virtual_account_info\": {\"virtual_account_number\": \"1900800000030637\"}, \"virtual_account_payment\": {\"date\": \"20230317154120\", \"identifier\": [{\"name\": \"REQUEST_ID\", \"value\": \"527001\"}, {\"name\": \"REFERENCE\", \"value\": \"78296\"}, {\"name\": \"CHANNEL_TYPE\", \"value\": \"6014\"}], \"reference_number\": \"78296\"}}",
                "ItemQty": 1,
                "ExpiredAt": "2023-03-17T09:11:20.436707Z",
                "CreatedAt": "2023-03-17T08:41:00.758175Z",
                "UpdatedAt": "2023-03-17T08:41:00.758175Z",
                "DeletedAt": null,
                "UserName": "Feryanti",
                "PhoneNumber": "628119199509",
                "MerchantId": 1,
                "DeliveryMethod": "PICKUP",
                "DeliveryRefId": null,
                "DeliveryUrl": null,
                "IsPaid": true,
                "PaymentMethod": "BCA-VA",
                "PaymentCode": "BCA-VA",
                "PaymentUrl": "",
                "Forwarded": null,
                "Name": "Lotte Grosir Fatmawati",
                "Address": "",
                "City": "",
                "Country": "",
                "MaxRadius": 0,
                "MerchantName": "",
                "Pic": "",
                "Admin": "",
                "IsActive": false,
                "ZipCode": "",
                "CategoryId": 0,
                "CategoryName": "",
                "MinStock": 0,
                "MaxSalesDays": 0,
                "Token": "",
                "MerchantID": 0,
                "State": "",
                "LocationName": "Jl. Pulau Sipura, RT.003/RW.010, Jatimakmur, Kec. Pd. Gede, Kota Bks, Jawa Barat 17413, Indonesia",
                "LocationNote": null,
                "AddressId": null,
                "ExpireAt": "0001-01-01T00:00:00Z",
                "OrderItem": null
            },
            {
                "Id": 148,
                "ReferenceId": "20230317UQmaQiX",
                "StoreId": 1,
                "UserId": 19,
                "UserTokenId": 238,
                "OrderStatus": "SUCCESSFUL",
                "TotalBeforeTax": 20000,
                "TotalTax": 2000,
                "DeliveryFee": 16000,
                "OrderFee": 1000,
                "PaymentFee": 0,
                "Total": 39000,
                "Metadata": "{\"order\": {\"amount\": 39000, \"invoice_number\": \"20230317UQmaQiX\"}, \"client\": {}, \"refund\": {\"date\": \"0001-01-01T00:00:00Z\"}, \"ovo_info\": {\"ovo_account_name\": \"\"}, \"ovo_void\": {}, \"security\": {}, \"ovo_payment\": {\"date\": \"\", \"status\": \"\", \"cash_used\": 0, \"cash_balance\": 0, \"response_code\": \"\", \"ovo_points_used\": 0, \"ovo_points_earned\": 0, \"ovo_points_balance\": 0}, \"additional_info\": {\"settlement\": [{\"type\": \"FIX\", \"value\": 22000, \"bank_account_settlement_id\": \"313213\"}, {\"type\": \"FIX\", \"value\": 17000, \"bank_account_settlement_id\": \"1\"}], \"hold_settlement\": true}, \"ovo_configuration\": {\"mid\": \"\", \"tid\": \"\", \"store_code\": \"\", \"merchant_id\": \"\"}, \"shopeepay_payment\": {\"status\": \"SUCCESS\", \"redirect_url_http\": \"https://sandbox.doku.com/integration/simulator/shopeepay/payment?amount=3900000&&invoiceNumber=20230317UQmaQiX&&mei=BRN-0298-1676891848212&&sei=BRN-0298-1676891848212&&token=vJZHlWHanZia6ozYnHsKUkAeDLiFG0MXHg2JlWFSy87mEvFtOkJWa46fRpINFEncbyPuDYpZXtkysiZUFTT2OqnmwfPQ30gW8DisPEVXY78xD6ZZC8OXMHUgLgw0dXdR&&returnUrl=https://jcc-file.jatismobile.com/thankyou\", \"transaction_status\": \"\", \"transaction_message\": \"\"}, \"shopeepay_configuration\": {\"store_ext_id\": \"BRN-0298-1676891848212\", \"merchant_ext_id\": \"BRN-0298-1676891848212\"}}",
                "ItemQty": 1,
                "ExpiredAt": "2023-03-17T08:55:21.533831Z",
                "CreatedAt": "2023-03-17T08:25:21.384825Z",
                "UpdatedAt": "2023-03-17T08:25:21.384825Z",
                "DeletedAt": null,
                "UserName": "Atha Dhaiffathin 2nd",
                "PhoneNumber": "628974500107",
                "MerchantId": 1,
                "DeliveryMethod": "grab",
                "DeliveryRefId": "WYB-1679044284690",
                "DeliveryUrl": "",
                "IsPaid": false,
                "PaymentMethod": "SHOPEEPAY",
                "PaymentCode": "SHOPEEPAY",
                "PaymentUrl": "https://sandbox.doku.com/integration/simulator/shopeepay/payment?amount=3900000&&invoiceNumber=20230317UQmaQiX&&mei=BRN-0298-1676891848212&&sei=BRN-0298-1676891848212&&token=vJZHlWHanZia6ozYnHsKUkAeDLiFG0MXHg2JlWFSy87mEvFtOkJWa46fRpINFEncbyPuDYpZXtkysiZUFTT2OqnmwfPQ30gW8DisPEVXY78xD6ZZC8OXMHUgLgw0dXdR&&returnUrl=https://jcc-file.jatismobile.com/thankyou",
                "Forwarded": null,
                "Name": "Lotte Grosir Fatmawati",
                "Address": "",
                "City": "",
                "Country": "",
                "MaxRadius": 0,
                "MerchantName": "",
                "Pic": "",
                "Admin": "",
                "IsActive": false,
                "ZipCode": "",
                "CategoryId": 0,
                "CategoryName": "",
                "MinStock": 0,
                "MaxSalesDays": 0,
                "Token": "",
                "MerchantID": 0,
                "State": "",
                "LocationName": "Graha Mitra Citra Blok H11/2, RT.10/RW.02, Panongan, Kec. Panongan, Kabupaten Tangerang, Banten 15710, Indonesia",
                "LocationNote": null,
                "AddressId": null,
                "ExpireAt": "0001-01-01T00:00:00Z",
                "OrderItem": null
            },
            {
                "Id": 146,
                "ReferenceId": "20230317SqMXfJy",
                "StoreId": 1,
                "UserId": 13,
                "UserTokenId": 229,
                "OrderStatus": "SUCCESSFUL",
                "TotalBeforeTax": 30000,
                "TotalTax": 3000,
                "DeliveryFee": 0,
                "OrderFee": 1000,
                "PaymentFee": 0,
                "Total": 34000,
                "Metadata": "{\"order\": {\"amount\": 34000, \"invoice_number\": \"20230317SqMXfJy\"}, \"channel\": {\"id\": \"VIRTUAL_ACCOUNT_BCA\", \"name\": \"\"}, \"service\": {\"id\": \"VIRTUAL_ACCOUNT\", \"name\": \"\"}, \"acquirer\": {\"id\": \"BCA\", \"name\": \"\"}, \"transaction\": {\"date\": \"2023-03-17T07:39:21Z\", \"status\": \"SUCCESS\", \"original_request_id\": \"79959a31-b31c-4452-b66f-a8ddabac77ca\"}, \"virtual_account_info\": {\"virtual_account_number\": \"1900800000030629\"}, \"virtual_account_payment\": {\"date\": \"20230317143921\", \"identifier\": [{\"name\": \"REQUEST_ID\", \"value\": \"432934\"}, {\"name\": \"REFERENCE\", \"value\": \"16217\"}, {\"name\": \"CHANNEL_TYPE\", \"value\": \"6014\"}], \"reference_number\": \"16217\"}}",
                "ItemQty": 2,
                "ExpiredAt": "2023-03-17T08:09:21.529046Z",
                "CreatedAt": "2023-03-17T07:38:18.626182Z",
                "UpdatedAt": "2023-03-17T07:38:18.626182Z",
                "DeletedAt": null,
                "UserName": "Feryanti",
                "PhoneNumber": "628119199509",
                "MerchantId": 1,
                "DeliveryMethod": "grab",
                "DeliveryRefId": null,
                "DeliveryUrl": null,
                "IsPaid": true,
                "PaymentMethod": "BCA-VA",
                "PaymentCode": "BCA-VA",
                "PaymentUrl": "",
                "Forwarded": null,
                "Name": "Lotte Grosir Fatmawati",
                "Address": "",
                "City": "",
                "Country": "",
                "MaxRadius": 0,
                "MerchantName": "",
                "Pic": "",
                "Admin": "",
                "IsActive": false,
                "ZipCode": "",
                "CategoryId": 0,
                "CategoryName": "",
                "MinStock": 0,
                "MaxSalesDays": 0,
                "Token": "",
                "MerchantID": 0,
                "State": "",
                "LocationName": "Jl. Raya Jatiwaringin No.108, RT.001/RW.001, Jatiwaringin, Kec. Pd. Gede, Kota Bks, Jawa Barat 17411, Indonesia",
                "LocationNote": null,
                "AddressId": null,
                "ExpireAt": "0001-01-01T00:00:00Z",
                "OrderItem": null
            },
            {
                "Id": 128,
                "ReferenceId": "20230315jgj4z8e",
                "StoreId": 1,
                "UserId": 13,
                "UserTokenId": 202,
                "OrderStatus": "SUCCESSFUL",
                "TotalBeforeTax": 15000,
                "TotalTax": 1500,
                "DeliveryFee": 0,
                "OrderFee": 1000,
                "PaymentFee": 0,
                "Total": 17500,
                "Metadata": "{\"order\": {\"amount\": 17500, \"invoice_number\": \"20230315jgj4z8e\"}, \"channel\": {\"id\": \"VIRTUAL_ACCOUNT_BCA\", \"name\": \"\"}, \"service\": {\"id\": \"VIRTUAL_ACCOUNT\", \"name\": \"\"}, \"acquirer\": {\"id\": \"BCA\", \"name\": \"\"}, \"transaction\": {\"date\": \"2023-03-15T09:14:56Z\", \"status\": \"SUCCESS\", \"original_request_id\": \"f7e416c6-46c0-438f-b129-35ab060beb8b\"}, \"virtual_account_info\": {\"virtual_account_number\": \"1900800000030450\"}, \"virtual_account_payment\": {\"date\": \"20230315161456\", \"identifier\": [{\"name\": \"REQUEST_ID\", \"value\": \"265402\"}, {\"name\": \"REFERENCE\", \"value\": \"28723\"}, {\"name\": \"CHANNEL_TYPE\", \"value\": \"6014\"}], \"reference_number\": \"28723\"}}",
                "ItemQty": 1,
                "ExpiredAt": "2023-03-15T09:44:56.947863Z",
                "CreatedAt": "2023-03-15T09:14:02.816491Z",
                "UpdatedAt": "2023-03-15T09:14:02.816491Z",
                "DeletedAt": null,
                "UserName": "Feryanti",
                "PhoneNumber": "628119199509",
                "MerchantId": 1,
                "DeliveryMethod": "grab",
                "DeliveryRefId": null,
                "DeliveryUrl": null,
                "IsPaid": true,
                "PaymentMethod": "BCA-VA",
                "PaymentCode": "BCA-VA",
                "PaymentUrl": "",
                "Forwarded": null,
                "Name": "Lotte Grosir Fatmawati",
                "Address": "",
                "City": "",
                "Country": "",
                "MaxRadius": 0,
                "MerchantName": "",
                "Pic": "",
                "Admin": "",
                "IsActive": false,
                "ZipCode": "",
                "CategoryId": 0,
                "CategoryName": "",
                "MinStock": 0,
                "MaxSalesDays": 0,
                "Token": "",
                "MerchantID": 0,
                "State": "",
                "LocationName": "Jl. H. Unus No.48, RT.002/RW.001, Larangan Utara, Kec. Larangan, Kota Tangerang, Banten 15154, Indonesia",
                "LocationNote": null,
                "AddressId": null,
                "ExpireAt": "0001-01-01T00:00:00Z",
                "OrderItem": null
            }
        ]
    },
    "error": "",
    "success": true,
    "total": 9
}